gdio/__init__.py
gdio/cgrib.py
gdio/commons.py
gdio/core.py
gdio/grib.py
gdio/hdf.py
gdio/netcdf.py
gdio/definitions/Table_1_4.py
gdio/definitions/Table_3_1.py
gdio/definitions/Table_4_4.py
gdio/definitions/Table_4_5.py
gdio/definitions/__init__.py
gdio/definitions/grib_namespace.py
tests/__init__.py
tests/test_commons.py
tests/test_core.py
tests/test_grib.py
tests/test_hdf.py
tests/test_netcdf.py
gdio-0.3.6.dist-info/LICENSE.md
gdio-0.3.6.dist-info/METADATA
gdio-0.3.6.dist-info/WHEEL
gdio-0.3.6.dist-info/top_level.txt
gdio-0.3.6.dist-info/RECORD
