Metadata-Version: 2.1
Name: gdio
Version: 0.3.6
Summary: Gridded data io library
Home-page: https://github.com/rodri90y/gdio
Download-URL: https://github.com/rodri90y/gdio/archive/v0.3.6.tar.gz
Author: Rodrigo Yamamoto
Author-email: codes@rodrigoyamamoto.com
License: MIT
Keywords: gdio,grib,netcdf,hdf5
Classifier: Programming Language :: Python :: 3
Classifier: License :: OSI Approved :: MIT License
Classifier: Operating System :: OS Independent
Requires-Python: ==3.9.0
License-File: LICENSE.md
Requires-Dist: numpy
Requires-Dist: netCDF4
Requires-Dist: h5py
Requires-Dist: eccodes
Requires-Dist: pyproj
